docuguru/__init__.py
docuguru/cli.py
docuguru/default.py
docuguru/html_to_pdf.py
docuguru/markdon_to_html.py
docuguru-0.1.0.dist-info/METADATA
docuguru-0.1.0.dist-info/WHEEL
docuguru-0.1.0.dist-info/entry_points.txt
docuguru-0.1.0.dist-info/RECORD
