Metadata-Version: 2.4
Name: docuguru
Version: 0.1.0
Summary: 
Author: Cristian Cubillos
Author-email: ccubillosreyes1@gmail.com
Requires-Python: >=3.12
Classifier: Programming Language :: Python :: 3
Classifier: Programming Language :: Python :: 3.12
Classifier: Programming Language :: Python :: 3.13
Classifier: Programming Language :: Python :: 3.14
Requires-Dist: jinja2 (>=3.1.6,<4.0.0)
Requires-Dist: markdown (>=3.10,<4.0)
Requires-Dist: pygments (>=2.19.2,<3.0.0)
Requires-Dist: typer (>=0.21.0,<0.22.0)
Requires-Dist: weasyprint (>=67.0,<68.0)
